Workbook

Sheet Daily Pacing
A1: CAMPAIGN DAILY PACING DASHBOARD
A3: Campaign Name: | B3: Enter Campaign Name | E3: Platform: | F3: Google Ads / Meta / LinkedIn / Snapchat | I3: Campaign ID: | J3: Enter ID
A4: Start Date: | B4: 45292 | E4: End Date: | F4: 45322 | I4: Total Budget: | J4: 10000
A5: Campaign Duration (Days): | B5: =F4-B4+1 | E5: Days Elapsed: | F5: =TODAY()-B4+1 | I5: Days Remaining: | J5: =F4-TODAY()
A7: Date | B7: Platform | C7: Impressions | D7: Clicks | E7: CTR % | F7: Conversions | G7: Conv Rate % | H7: Spend | I7: CPM | J7: CPC | K7: CPA | L7: ROAS | M7: Revenue | N7: Notes
A8: 45292 | B8: Google Ads | E8: =IF(C8=0,0,D8/C8) | G8: =IF(D8=0,0,F8/D8) | I8: =IF(C8=0,0,(H8/C8)*1000) | J8: =IF(D8=0,0,H8/D8) | K8: =IF(F8=0,0,H8/F8) | L8: =IF(H8=0,0,M8/H8)
A9: 45293 | B9: Meta | E9: =IF(C9=0,0,D9/C9) | G9: =IF(D9=0,0,F9/D9) | I9: =IF(C9=0,0,(H9/C9)*1000) | J9: =IF(D9=0,0,H9/D9) | K9: =IF(F9=0,0,H9/F9) | L9: =IF(H9=0,0,M9/H9)
A10: 45294 | B10: LinkedIn | E10: =IF(C10=0,0,D10/C10) | G10: =IF(D10=0,0,F10/D10) | I10: =IF(C10=0,0,(H10/C10)*1000) | J10: =IF(D10=0,0,H10/D10) | K10: =IF(F10=0,0,H10/F10) | L10: =IF(H10=0,0,M10/H10)
A11: 45295 | B11: Snapchat | E11: =IF(C11=0,0,D11/C11) | G11: =IF(D11=0,0,F11/D11) | I11: =IF(C11=0,0,(H11/C11)*1000) | J11: =IF(D11=0,0,H11/D11) | K11: =IF(F11=0,0,H11/F11) | L11: =IF(H11=0,0,M11/H11)
A12: 45296 | B12: Google Ads | E12: =IF(C12=0,0,D12/C12) | G12: =IF(D12=0,0,F12/D12) | I12: =IF(C12=0,0,(H12/C12)*1000) | J12: =IF(D12=0,0,H12/D12) | K12: =IF(F12=0,0,H12/F12) | L12: =IF(H12=0,0,M12/H12)
A13: 45297 | B13: Meta | E13: =IF(C13=0,0,D13/C13) | G13: =IF(D13=0,0,F13/D13) | I13: =IF(C13=0,0,(H13/C13)*1000) | J13: =IF(D13=0,0,H13/D13) | K13: =IF(F13=0,0,H13/F13) | L13: =IF(H13=0,0,M13/H13)
A14: 45298 | B14: LinkedIn | E14: =IF(C14=0,0,D14/C14) | G14: =IF(D14=0,0,F14/D14) | I14: =IF(C14=0,0,(H14/C14)*1000) | J14: =IF(D14=0,0,H14/D14) | K14: =IF(F14=0,0,H14/F14) | L14: =IF(H14=0,0,M14/H14)
A15: 45299 | B15: Snapchat | E15: =IF(C15=0,0,D15/C15) | G15: =IF(D15=0,0,F15/D15) | I15: =IF(C15=0,0,(H15/C15)*1000) | J15: =IF(D15=0,0,H15/D15) | K15: =IF(F15=0,0,H15/F15) | L15: =IF(H15=0,0,M15/H15)
A16: 45300 | B16: Google Ads | E16: =IF(C16=0,0,D16/C16) | G16: =IF(D16=0,0,F16/D16) | I16: =IF(C16=0,0,(H16/C16)*1000) | J16: =IF(D16=0,0,H16/D16) | K16: =IF(F16=0,0,H16/F16) | L16: =IF(H16=0,0,M16/H16)
A17: 45301 | B17: Meta | E17: =IF(C17=0,0,D17/C17) | G17: =IF(D17=0,0,F17/D17) | I17: =IF(C17=0,0,(H17/C17)*1000) | J17: =IF(D17=0,0,H17/D17) | K17: =IF(F17=0,0,H17/F17) | L17: =IF(H17=0,0,M17/H17)
A18: 45302 | B18: LinkedIn | E18: =IF(C18=0,0,D18/C18) | G18: =IF(D18=0,0,F18/D18) | I18: =IF(C18=0,0,(H18/C18)*1000) | J18: =IF(D18=0,0,H18/D18) | K18: =IF(F18=0,0,H18/F18) | L18: =IF(H18=0,0,M18/H18)
A19: 45303 | B19: Snapchat | E19: =IF(C19=0,0,D19/C19) | G19: =IF(D19=0,0,F19/D19) | I19: =IF(C19=0,0,(H19/C19)*1000) | J19: =IF(D19=0,0,H19/D19) | K19: =IF(F19=0,0,H19/F19) | L19: =IF(H19=0,0,M19/H19)
A20: 45304 | B20: Google Ads | E20: =IF(C20=0,0,D20/C20) | G20: =IF(D20=0,0,F20/D20) | I20: =IF(C20=0,0,(H20/C20)*1000) | J20: =IF(D20=0,0,H20/D20) | K20: =IF(F20=0,0,H20/F20) | L20: =IF(H20=0,0,M20/H20)
A22: TOTALS | C22: =SUM(C8:C20) | D22: =SUM(D8:D20) | E22: =IF(C22=0,0,D22/C22) | F22: =SUM(F8:F20) | G22: =IF(D22=0,0,F22/D22) | H22: =SUM(H8:H20) | I22: =IF(C22=0,0,(H22/C22)*1000) | J22: =IF(D22=0,0,H22/D22) | K22: =IF(F22=0,0,H22/F22) | L22: =IF(H22=0,0,M22/H22) | M22: =SUM(M8:M20)
A24: PACING ANALYSIS | H24: PLATFORM BREAKDOWN
A26: Metric | B26: Target | C26: Actual | D26: Variance | E26: % of Target | F26: Status | H26: Platform | I26: Impressions | J26: Clicks | K26: Conversions | L26: Spend | M26: CTR % | N26: CPA
A27: Budget Spent | B27: =(F5/B5)*J4 | C27: =H22 | D27: =C27-B27 | E27: =IF(B27=0,0,C27/B27) | F27: =IF(E27>1.1,"Over Pacing",IF(E27<0.9,"Under Pacing","On Track")) | H27: Google Ads | I27: =SUMIF(B:B,H27,C:C) | J27: =SUMIF(B:B,H27,D:D) | K27: =SUMIF(B:B,H27,F:F) | L27: =SUMIF(B:B,H27,H:H) | M27: =IF(I27=0,0,J27/I27) | N27: =IF(K27=0,0,L27/K27)
A28: Time Progress | B28: 100% | C28: =F5/B5 | D28: =C28-100% | E28: =C28 | F28: =IF(F5>B5,"Completed","Active") | H28: Meta | I28: =SUMIF(B:B,H28,C:C) | J28: =SUMIF(B:B,H28,D:D) | K28: =SUMIF(B:B,H28,F:F) | L28: =SUMIF(B:B,H28,H:H) | M28: =IF(I28=0,0,J28/I28) | N28: =IF(K28=0,0,L28/K28)
A29: Budget Utilization | B29: =J4 | C29: =H22 | D29: =J4-H22 | E29: =IF(B29=0,0,C29/B29) | F29: =IF(E29>1,"Over Budget",IF(E29>0.9,"Near Limit","Healthy")) | H29: LinkedIn | I29: =SUMIF(B:B,H29,C:C) | J29: =SUMIF(B:B,H29,D:D) | K29: =SUMIF(B:B,H29,F:F) | L29: =SUMIF(B:B,H29,H:H) | M29: =IF(I29=0,0,J29/I29) | N29: =IF(K29=0,0,L29/K29)
A30: Pacing Index | B30: 1.0 | C30: =IF(C28=0,0,E27/C28) | D30: =C30-1 | E30: =C30 | F30: =IF(C30>1.15,"Critical Over",IF(C30>1.05,"Moderate Over",IF(C30<0.85,"Critical Under",IF(C30<0.95,"Moderate Under","Optimal")))) | H30: Snapchat | I30: =SUMIF(B:B,H30,C:C) | J30: =SUMIF(B:B,H30,D:D) | K30: =SUMIF(B:B,H30,F:F) | L30: =SUMIF(B:B,H30,H:H) | M30: =IF(I30=0,0,J30/I30) | N30: =IF(K30=0,0,L30/K30)

Sheet Weekly Pacing
A1: CAMPAIGN WEEKLY PACING DASHBOARD
A3: Campaign Name: | B3: ='Daily Pacing'!B3 | E3: Platform: | F3: ='Daily Pacing'!F3 | I3: Campaign ID: | J3: ='Daily Pacing'!J3
A4: Start Date: | B4: ='Daily Pacing'!B4 | E4: End Date: | F4: ='Daily Pacing'!F4 | I4: Total Budget: | J4: ='Daily Pacing'!J4
A5: Total Weeks: | B5: =ROUNDUP((F4-B4+1)/7,0) | E5: Current Week: | F5: =ROUNDUP((TODAY()-B4+1)/7,0) | I5: Weeks Remaining: | J5: =B5-F5
A7: Week # | B7: Week Start | C7: Week End | D7: Platform | E7: Impressions | F7: Clicks | G7: CTR % | H7: Conversions | I7: Conv Rate % | J7: Spend | K7: CPM | L7: CPC | M7: CPA | N7: ROAS | O7: Notes
A8: 1 | B8: 45292 | C8: 45298 | D8: All Platforms | G8: =IF(E8=0,0,F8/E8) | I8: =IF(F8=0,0,H8/F8) | K8: =IF(E8=0,0,(J8/E8)*1000) | L8: =IF(F8=0,0,J8/F8) | M8: =IF(H8=0,0,J8/H8) | N8: =IF(J8=0,0,O8/J8)
A9: 2 | B9: 45299 | C9: 45305 | D9: All Platforms | G9: =IF(E9=0,0,F9/E9) | I9: =IF(F9=0,0,H9/F9) | K9: =IF(E9=0,0,(J9/E9)*1000) | L9: =IF(F9=0,0,J9/F9) | M9: =IF(H9=0,0,J9/H9) | N9: =IF(J9=0,0,O9/J9)
A10: 3 | B10: 45306 | C10: 45312 | D10: All Platforms | G10: =IF(E10=0,0,F10/E10) | I10: =IF(F10=0,0,H10/F10) | K10: =IF(E10=0,0,(J10/E10)*1000) | L10: =IF(F10=0,0,J10/F10) | M10: =IF(H10=0,0,J10/H10) | N10: =IF(J10=0,0,O10/J10)
A11: 4 | B11: 45313 | C11: 45319 | D11: All Platforms | G11: =IF(E11=0,0,F11/E11) | I11: =IF(F11=0,0,H11/F11) | K11: =IF(E11=0,0,(J11/E11)*1000) | L11: =IF(F11=0,0,J11/F11) | M11: =IF(H11=0,0,J11/H11) | N11: =IF(J11=0,0,O11/J11)
A12: 5 | B12: 45320 | C12: 45326 | D12: All Platforms | G12: =IF(E12=0,0,F12/E12) | I12: =IF(F12=0,0,H12/F12) | K12: =IF(E12=0,0,(J12/E12)*1000) | L12: =IF(F12=0,0,J12/F12) | M12: =IF(H12=0,0,J12/H12) | N12: =IF(J12=0,0,O12/J12)
A13: 6 | B13: 45327 | C13: 45333 | D13: All Platforms | G13: =IF(E13=0,0,F13/E13) | I13: =IF(F13=0,0,H13/F13) | K13: =IF(E13=0,0,(J13/E13)*1000) | L13: =IF(F13=0,0,J13/F13) | M13: =IF(H13=0,0,J13/H13) | N13: =IF(J13=0,0,O13/J13)
A14: 7 | B14: 45334 | C14: 45340 | D14: All Platforms | G14: =IF(E14=0,0,F14/E14) | I14: =IF(F14=0,0,H14/F14) | K14: =IF(E14=0,0,(J14/E14)*1000) | L14: =IF(F14=0,0,J14/F14) | M14: =IF(H14=0,0,J14/H14) | N14: =IF(J14=0,0,O14/J14)
A15: 8 | B15: 45341 | C15: 45347 | D15: All Platforms | G15: =IF(E15=0,0,F15/E15) | I15: =IF(F15=0,0,H15/F15) | K15: =IF(E15=0,0,(J15/E15)*1000) | L15: =IF(F15=0,0,J15/F15) | M15: =IF(H15=0,0,J15/H15) | N15: =IF(J15=0,0,O15/J15)
A17: TOTALS | E17: =SUM(E8:E15) | F17: =SUM(F8:F15) | G17: =IF(E17=0,0,F17/E17) | H17: =SUM(H8:H15) | I17: =IF(F17=0,0,H17/F17) | J17: =SUM(J8:J15) | K17: =IF(E17=0,0,(J17/E17)*1000) | L17: =IF(F17=0,0,J17/F17) | M17: =IF(H17=0,0,J17/H17) | N17: =IF(J17=0,0,O17/J17)
A19: WEEKLY PACING ANALYSIS | H19: WEEK-OVER-WEEK TRENDS
A21: Metric | B21: Target | C21: Actual | D21: Variance | E21: % of Target | F21: Status | H21: Week | I21: Spend | J21: WoW Change | K21: Conversions | L21: WoW Change | M21: CPA | N21: WoW Change | O21: ROAS
A22: Budget Spent | B22: =(F5/B5)*J4 | C22: =J17 | D22: =C22-B22 | E22: =IF(B22=0,0,C22/B22) | F22: =IF(E22>1.1,"Over Pacing",IF(E22<0.9,"Under Pacing","On Track")) | H22: Week 1 | I22: =J8 | K22: =H8 | M22: =M8 | O22: =N8
A23: Week Progress | B23: 100% | C23: =F5/B5 | D23: =C23-100% | E23: =C23 | F23: =IF(F5>B5,"Completed","Active") | H23: Week 2 | I23: =J9 | J23: =IF(I22=0,0,(I23-I22)/I22) | K23: =H9 | L23: =IF(K22=0,0,(K23-K22)/K22) | M23: =M9 | N23: =IF(M22=0,0,(M23-M22)/M22) | O23: =N9
A24: Avg Weekly Spend | B24: =J4/B5 | C24: =J17/F5 | D24: =C24-B24 | E24: =IF(B24=0,0,C24/B24) | F24: =IF(E24>1.1,"Over",IF(E24<0.9,"Under","Normal")) | H24: Week 3 | I24: =J10 | J24: =IF(I23=0,0,(I24-I23)/I23) | K24: =H10 | L24: =IF(K23=0,0,(K24-K23)/K23) | M24: =M10 | N24: =IF(M23=0,0,(M24-M23)/M23) | O24: =N10
A25: Pacing Index | B25: 1.0 | C25: =IF(C23=0,0,E22/C23) | D25: =C25-1 | E25: =C25 | F25: =IF(C25>1.15,"Critical Over",IF(C25>1.05,"Moderate Over",IF(C25<0.85,"Critical Under",IF(C25<0.95,"Moderate Under","Optimal")))) | H25: Week 4 | I25: =J11 | J25: =IF(I24=0,0,(I25-I24)/I24) | K25: =H11 | L25: =IF(K24=0,0,(K25-K24)/K24) | M25: =M11 | N25: =IF(M24=0,0,(M25-M24)/M24) | O25: =N11
H26: Week 5 | I26: =J12 | J26: =IF(I25=0,0,(I26-I25)/I25) | K26: =H12 | L26: =IF(K25=0,0,(K26-K25)/K25) | M26: =M12 | N26: =IF(M25=0,0,(M26-M25)/M25) | O26: =N12
H27: Week 6 | I27: =J13 | J27: =IF(I26=0,0,(I27-I26)/I26) | K27: =H13 | L27: =IF(K26=0,0,(K27-K26)/K26) | M27: =M13 | N27: =IF(M26=0,0,(M27-M26)/M26) | O27: =N13
H28: Week 7 | I28: =J14 | J28: =IF(I27=0,0,(I28-I27)/I27) | K28: =H14 | L28: =IF(K27=0,0,(K28-K27)/K27) | M28: =M14 | N28: =IF(M27=0,0,(M28-M27)/M27) | O28: =N14
H29: Week 8 | I29: =J15 | J29: =IF(I28=0,0,(I29-I28)/I28) | K29: =H15 | L29: =IF(K28=0,0,(K29-K28)/K28) | M29: =M15 | N29: =IF(M28=0,0,(M29-M28)/M28) | O29: =N15

Sheet Data Dictionary
A1: DATA DICTIONARY & AI AGENT GUIDE
A3: Field Name | B3: Description | C3: Data Type | D3: Formula/Notes
A4: Impressions | B4: Number of times ad was displayed | C4: Integer | D4: Sum from platform
A5: Clicks | B5: Number of ad clicks | C5: Integer | D5: Sum from platform
A6: CTR % | B6: Click-through rate | C6: Percentage | D6: =Clicks/Impressions
A7: Conversions | B7: Number of conversions | C7: Integer | D7: Sum from platform
A8: Conv Rate % | B8: Conversion rate | C8: Percentage | D8: =Conversions/Clicks
A9: Spend | B9: Total ad spend | C9: Currency | D9: Sum from platform
A10: CPM | B10: Cost per thousand impressions | C10: Currency | D10: =(Spend/Impressions)*1000
A11: CPC | B11: Cost per click | C11: Currency | D11: =Spend/Clicks
A12: CPA | B12: Cost per acquisition | C12: Currency | D12: =Spend/Conversions
A13: ROAS | B13: Return on ad spend | C13: Decimal | D13: =Revenue/Spend
A14: Revenue | B14: Total revenue generated | C14: Currency | D14: From conversion tracking
A15: Pacing Index | B15: Budget pacing indicator | C15: Decimal | D15: =(% Budget Spent)/(% Time Elapsed)
A17: PACING INDEX GUIDE
A18: > 1.15 | B18: Critical Over-pacing | D18: Immediate action needed
A19: 1.05 - 1.15 | B19: Moderate Over-pacing | D19: Monitor closely
A20: 0.95 - 1.05 | B20: Optimal Pacing | D20: On track
A21: 0.85 - 0.95 | B21: Moderate Under-pacing | D21: Consider increasing spend
A22: < 0.85 | B22: Critical Under-pacing | D22: Significant underspend
A24: AI AGENT INPUT GUIDELINES
A26: Sheet | B26: Update Frequency | C26: Key Cells | D26: Notes
A27: Daily Pacing | B27: Daily | C27: B3:J4 (Campaign Info) | D27: Yellow cells are inputs
A28: Daily Pacing | B28: Daily | C28: Rows 8-20 | D28: Add daily performance data
A29: Weekly Pacing | B29: Weekly | C29: Rows 8-15 | D29: Add weekly aggregate data
A31: AUTOMATION TIPS
A32: 1. Date Validation | B32: Ensure dates are sequential
A33: 2. Platform Matching | B33: Use exact platform names
A34: 3. Zero Handling | B34: All formulas handle division by zero
A35: 4. Currency Format | B35: Use consistent currency formatting

Sheet Campaign_Data
A1: date | B1: campaign_id | C1: campaign_name | D1: spend | E1: impressions | F1: clicks | G1: conversions | H1: revenue | I1: ctr | J1: cpc | K1: cpm | L1: cpa | M1: roas | N1: conversion_rate | O1: budget_total | P1: budget_spent | Q1: budget_remaining | R1: budget_spent_pct | S1: budget_remaining_pct | T1: daily_budget | U1: days_remaining
A2: 2025-12-04 | B2: CAMP001 | C2: Q4 Brand Campaign | D2: 1500.5 | E2: 45000 | F2: 450 | G2: 25 | H2: 7500 | I2: 1 | J2: 3.33 | K2: 33.34 | L2: 60.02 | M2: 5 | N2: 5.56 | O2: 50000 | P2: 1500.5 | Q2: 48499.5 | R2: 3 | S2: 97 | T2: 543.48 | U2: -338
A3: 2025-12-04 | B3: CAMP002 | C3: Holiday Sales Push | D3: 2800.75 | E3: 68000 | F3: 820 | G3: 45 | H3: 14000 | I3: 1.21 | J3: 3.42 | K3: 41.19 | L3: 62.24 | M3: 5 | N3: 5.49 | O3: 75000 | P3: 2800.75 | Q3: 72199.25 | R3: 3.73 | S3: 96.27 | T3: 1875 | U3: -344
A4: 2025-12-04 | B4: CAMP003 | C4: Product Launch | D4: 950.25 | E4: 28000 | F4: 280 | G4: 18 | H4: 5400 | I4: 1 | J4: 3.39 | K4: 33.94 | L4: 52.79 | M4: 5.68 | N4: 6.43 | O4: 30000 | P4: 950.25 | Q4: 29049.75 | R4: 3.17 | S4: 96.83 | T4: 967.74 | U4: -338
A5: 2025-12-04 | B5: CAMP004 | C5: Retargeting Campaign | D5: 450 | E5: 15000 | F5: 180 | G5: 12 | H5: 3600 | I5: 1.2 | J5: 2.5 | K5: 30 | L5: 37.5 | M5: 8 | N5: 6.67 | O5: 15000 | P5: 450 | Q5: 14550 | R5: 3 | S5: 97 | T5: 245.9 | U5: -338
A6: 2025-12-04 | B6: CAMP005 | C6: Lead Generation | D6: 1200 | E6: 35000 | F6: 420 | G6: 28 | H6: 8400 | I6: 1.2 | J6: 2.86 | K6: 34.29 | L6: 42.86 | M6: 7 | N6: 6.67 | O6: 40000 | P6: 1200 | Q6: 38800 | R6: 3 | S6: 97 | T6: 512.82 | U6: -338
